pymsi/__init__.py
pymsi/__main__.py
pymsi/_version.py
pymsi/category.py
pymsi/codepage.py
pymsi/column.py
pymsi/constants.py
pymsi/package.py
pymsi/propset.py
pymsi/py.typed
pymsi/reader.py
pymsi/streamname.py
pymsi/stringpool.py
pymsi/summary.py
pymsi/table.py
pymsi/tables.py
pymsi/timestamp.py
pymsi/msi/__init__.py
pymsi/msi/component.py
pymsi/msi/directory.py
pymsi/msi/file.py
pymsi/msi/icon.py
pymsi/msi/media.py
pymsi/msi/msi.py
pymsi/msi/registry.py
pymsi/msi/remove_file.py
pymsi/msi/shortcut.py
pymsi/thirdparty/refinery/__init__.py
pymsi/thirdparty/refinery/array.py
pymsi/thirdparty/refinery/cab.py
pymsi/thirdparty/refinery/chunks.py
pymsi/thirdparty/refinery/lzx.py
pymsi/thirdparty/refinery/structures.py
pymsi/thirdparty/refinery/types.py
python_msi-0.0.0b3.dist-info/METADATA
python_msi-0.0.0b3.dist-info/WHEEL
python_msi-0.0.0b3.dist-info/entry_points.txt
python_msi-0.0.0b3.dist-info/licenses/LICENSE
python_msi-0.0.0b3.dist-info/licenses/NOTICE
python_msi-0.0.0b3.dist-info/RECORD
