Metadata-Version: 2.4
Name: python-msi
Version: 0.0.0b3
Summary: A pure Python library for reading and manipulating Windows Installer (MSI) files. Based on the rust msi crate and msitools utilities
Project-URL: Homepage, https://github.com/nightlark/pymsi
Project-URL: Discussions, https://github.com/nightlark/pymsi/discussions
Project-URL: Documentation, https://pymsi.readthedocs.io/en/latest/
Project-URL: Issue Tracker, https://github.com/nightlark/pymsi/issues
Project-URL: Source Code, https://github.com/nightlark/pymsi
Author-email: Asriel Camora <asriel@camora.dev>, Ryan Mast <mast.ryan@gmail.com>
Maintainer-email: Asriel Camora <asriel@camora.dev>, Ryan Mast <mast.ryan@gmail.com>
License-Expression: MIT
License-File: LICENSE
License-File: NOTICE
Keywords: installer,msi,ole,pe
Classifier: Development Status :: 4 - Beta
Classifier: Environment :: Console
Classifier: Operating System :: MacOS
Classifier: Operating System :: Microsoft :: Windows
Classifier: Operating System :: POSIX :: Linux
Classifier: Programming Language :: Python :: 3
Classifier: Programming Language :: Python :: 3 :: Only
Classifier: Programming Language :: Python :: 3.8
Classifier: Programming Language :: Python :: 3.9
Classifier: Programming Language :: Python :: 3.10
Classifier: Programming Language :: Python :: 3.11
Classifier: Programming Language :: Python :: 3.12
Classifier: Programming Language :: Python :: 3.13
Classifier: Programming Language :: Python :: 3.14
Classifier: Programming Language :: Python :: 3.15
Classifier: Topic :: Software Development
Classifier: Topic :: System
Classifier: Topic :: Utilities
Requires-Python: >=3.8
Requires-Dist: olefile
Provides-Extra: dev
Requires-Dist: build; extra == 'dev'
Requires-Dist: pre-commit; extra == 'dev'
Provides-Extra: docs
Requires-Dist: myst-parser; extra == 'docs'
Requires-Dist: sphinx; extra == 'docs'
Provides-Extra: test
Requires-Dist: pytest; extra == 'test'
